MANIFEST.in
README.txt
setup.cfg
setup.py
collective/__init__.py
collective.multisitepanel.egg-info/PKG-INFO
collective.multisitepanel.egg-info/SOURCES.txt
collective.multisitepanel.egg-info/dependency_links.txt
collective.multisitepanel.egg-info/entry_points.txt
collective.multisitepanel.egg-info/namespace_packages.txt
collective.multisitepanel.egg-info/not-zip-safe
collective.multisitepanel.egg-info/requires.txt
collective.multisitepanel.egg-info/top_level.txt
collective/multisitepanel/__init__.py
collective/multisitepanel/configure.zcml
collective/multisitepanel/profiles.zcml
collective/multisitepanel/utils.py
collective/multisitepanel/Extensions/Install.py
collective/multisitepanel/Extensions/__init__.py
collective/multisitepanel/browser/__init__.py
collective/multisitepanel/browser/configure.zcml
collective/multisitepanel/browser/interfaces.py
collective/multisitepanel/browser/msp_contents.py
collective/multisitepanel/browser/msp_panel.py
collective/multisitepanel/browser/msp_products.py
collective/multisitepanel/browser/msp_sitemap.py
collective/multisitepanel/browser/msp_users.py
collective/multisitepanel/browser/multisitebase.py
collective/multisitepanel/browser/javascript/jquery.tablehover.js
collective/multisitepanel/browser/javascript/multisitepanel.js
collective/multisitepanel/browser/stylesheets/main.css
collective/multisitepanel/browser/templates/msp_contents_details.pt
collective/multisitepanel/browser/templates/msp_contents_table.pt
collective/multisitepanel/browser/templates/msp_panel.pt
collective/multisitepanel/browser/templates/msp_products_details.pt
collective/multisitepanel/browser/templates/msp_products_table.pt
collective/multisitepanel/browser/templates/skeleton.pt
collective/multisitepanel/browser/templates/users_dashboard.pt
collective/multisitepanel/locales/it/LC_MESSAGES/collective.multisitepanel.po
collective/multisitepanel/profiles/default/actionicons.xml
collective/multisitepanel/profiles/default/controlpanel.xml
collective/multisitepanel/profiles/default/cssregistry.xml
collective/multisitepanel/profiles/default/jsregistry.xml
collective/multisitepanel/profiles/default/metadata.xml
collective/multisitepanel/profiles/default/toolset.xml
collective/multisitepanel/profiles/uninstall/controlpanel.xml