Metadata-Version: 1.0
Name: collective.multisitepanel
Version: 0.3
Summary: A panel for the administration of differents Plone site over the same Zope installation
Home-page: http://pypi.python.org/pypi/collective.multisitepanel
Author: Giacomo Spettoli
Author-email: giacomo@spettoli.com
License: GPL
Keywords: web zope plone
Platform: UNKNOWN
Classifier: Development Status :: 5 - Production/Stable
Classifier: Environment :: Web Environment
Classifier: Framework :: Plone
Classifier: Framework :: Zope2
Classifier: License :: OSI Approved :: GNU General Public License (GPL)
Classifier: Operating System :: OS Independent
Classifier: Programming Language :: Python
Classifier: Topic :: Software Development :: Libraries :: Python Modules
